metaexpert/__init__.py
metaexpert/__version__.py
metaexpert/_market.py
metaexpert/_process.py
metaexpert/_trade.py
metaexpert/arguments.py
metaexpert/config.py
metaexpert/expert.py
metaexpert/py.typed
metaexpert-0.1.0.dist-info/METADATA
metaexpert-0.1.0.dist-info/WHEEL
metaexpert-0.1.0.dist-info/licenses/LICENSE
metaexpert-0.1.0.dist-info/RECORD
