Metadata-Version: 2.4
Name: metaexpert
Version: 0.1.0
Summary: MetaExpert library
Project-URL: homepage, https://teratron.github.io/metaexpert
Project-URL: documentation, https://teratron.github.io/metaexpert/docs
Project-URL: github, https://github.com/teratron/metaexpert
Project-URL: repository, https://github.com/teratron/metaexpert.git
Author-email: Oleg Alexandrov <alexandrovoleg.ru@gmail.com>
License: MIT License
License-File: LICENSE
Keywords: binance,crypto,ta-lib,technical analysis,trading
Requires-Python: >=3.11
Requires-Dist: binance-connector>=3.12.0
Requires-Dist: flask>=3.1.0
Requires-Dist: lightweight-charts>=2.1
Requires-Dist: numpy>=2.2.4
Requires-Dist: pandas>=2.2.3
Requires-Dist: ta-lib==0.6.3
